img2data/__init__.py
img2data/img2data.py
img2data-0.0.1.dist-info/METADATA
img2data-0.0.1.dist-info/WHEEL
img2data-0.0.1.dist-info/top_level.txt
img2data-0.0.1.dist-info/RECORD
