Metadata-Version: 2.1
Name: img2data
Version: 0.0.1
Summary: Divide a number of handwritten digits in one image into individual images.
Home-page: https://github.com/dltpdn/img2data
Author: julmubm
Author-email: dltpdn@gmail.com
Classifier: Programming Language :: Python :: 3
Classifier: License :: OSI Approved :: MIT License
Classifier: Operating System :: OS Independent
Requires-Python: >=3.6
Requires-Dist: opencv-python
Requires-Dist: numpy
